src/__init__.py
src/constained_satisfaction.py
src/parser.py
src/priority_queue.py
src/search.py
AutoReason-0.0.2.dist-info/LICENSE
AutoReason-0.0.2.dist-info/METADATA
AutoReason-0.0.2.dist-info/WHEEL
AutoReason-0.0.2.dist-info/top_level.txt
AutoReason-0.0.2.dist-info/RECORD
